posthook/__init__.py
posthook/cli.py
posthook/installer.py
posthook/jenkins.py
posthook/hooks/post-commit
posthook/hooks/prepare-commit-msg
posthook-0.1.2.dist-info/METADATA
posthook-0.1.2.dist-info/WHEEL
posthook-0.1.2.dist-info/entry_points.txt
posthook-0.1.2.dist-info/top_level.txt
posthook-0.1.2.dist-info/RECORD
